Fuzz_output/__init__.py
Fuzz_output/main.py
Fuzzy_Output_EVAMortus-0.0.23.dist-info/LICENSE
Fuzzy_Output_EVAMortus-0.0.23.dist-info/METADATA
Fuzzy_Output_EVAMortus-0.0.23.dist-info/WHEEL
Fuzzy_Output_EVAMortus-0.0.23.dist-info/top_level.txt
Fuzzy_Output_EVAMortus-0.0.23.dist-info/RECORD
