Metadata-Version: 2.1
Name: Fuzzy-Output-EVAMortus
Version: 0.0.23
Summary: Fuzzy output module
Home-page: 
Author: Ermakov Vitaliy
Author-email: blackcheshireshusband@yandex.ru
Classifier: Programming Language :: Python :: 3.9
Classifier: License :: OSI Approved :: MIT License
Classifier: Operating System :: OS Independent
Requires-Python: >=3.9
License-File: LICENSE
